__init__.py
test.py
ReminderController/ReminderCategorizer.py
ReminderController/ReminderManagerService.py
ReminderController/ReminderOccurrence.py
ReminderNotifier/ReminderNotifier.py
reminderlib-0.0.5.dist-info/LICENSE.txt
reminderlib-0.0.5.dist-info/METADATA
reminderlib-0.0.5.dist-info/WHEEL
reminderlib-0.0.5.dist-info/top_level.txt
reminderlib-0.0.5.dist-info/RECORD
