Metadata-Version: 2.1
Name: reminderlib
Version: 0.0.5
Summary: Sample reminder library for AWS dynamodb
Home-page: UNKNOWN
Author: Jayashathiskumar Jayakumar
Author-email: x20154810@student.ncirl.ie
License: UNKNOWN
Platform: UNKNOWN
Classifier: Development Status :: 1 - Planning
Classifier: Intended Audience :: Education
Classifier: Operating System :: OS Independent
Classifier: License :: OSI Approved :: MIT License
Classifier: Programming Language :: Python :: 3
Requires-Dist: boto3
Requires-Dist: botocore
Requires-Dist: aws-logging-handlers
